django_localdevstorage-0.5.dist-info/DESCRIPTION.rst
django_localdevstorage-0.5.dist-info/METADATA
django_localdevstorage-0.5.dist-info/metadata.json
django_localdevstorage-0.5.dist-info/RECORD
django_localdevstorage-0.5.dist-info/top_level.txt
django_localdevstorage-0.5.dist-info/WHEEL
localdevstorage/__init__.py
localdevstorage/base.py
localdevstorage/http.py
localdevstorage/models.py
localdevstorage/sftp.py
localdevstorage/tests/__init__.py
localdevstorage/tests/test_http.py
localdevstorage/tests/test_settings.py
