Metadata-Version: 2.0
Name: django-localdevstorage
Version: 0.5
Summary: A Django storage backend for local development that downloads files from the live site on the fly.
Home-page: https://github.com/piquadrat/django-localdevstorage
Author: Benjamin Wohlwend
Author-email: piquadrat@gmail.com
License: UNKNOWN
Platform: UNKNOWN
Classifier: Development Status :: 3 - Alpha
Classifier: Framework :: Django
Classifier: Intended Audience :: Developers
Classifier: License :: OSI Approved :: BSD License
Classifier: Operating System :: OS Independent
Classifier: Programming Language :: Python :: 2.6
Classifier: Programming Language :: Python :: 2.7
Classifier: Programming Language :: Python :: 3.3
Classifier: Programming Language :: Python :: 3.4
Classifier: Topic :: Software Development
Classifier: Topic :: Internet :: WWW/HTTP :: Dynamic Content
Requires-Dist: Django (>=1.2)
Requires-Dist: requests (>=1.0)
